{
  "mock": {
    "owner": "46321051",
    "mockUrl": "https://e650ff6c-48e9-43d7-9e6c-c08a44a4368d.mock.pstmn.io",
    "id": "e650ff6c-48e9-43d7-9e6c-c08a44a4368d",
    "environment": null,
    "createdAt": "2026-02-16T21:00:31.000Z",
    "updatedAt": "2026-02-16T21:00:31.000Z",
    "config": {
      "matchWildcards": true,
      "serverResponseId": null,
      "headers": [],
      "delay": null,
      "matchBody": false,
      "matchHeader": false,
      "matchQueryParams": true
    },
    "collection": "46321051-f81dee69-d4e0-4ba7-9469-515838d3b802",
    "uid": "46321051-e650ff6c-48e9-43d7-9e6c-c08a44a4368d",
    "name": "C2mApiV2MockServer"
  }
}
